model_compression/__init__.py
model_compression/compress.py
model_compression_777-0.1.2.dist-info/WHEEL
model_compression_777-0.1.2.dist-info/METADATA
model_compression_777-0.1.2.dist-info/RECORD
